langgraph/checkpoint/aerospike/__init__.py
langgraph/checkpoint/aerospike/saver.py
langgraph_checkpoint_aerospike-0.1.0.dist-info/METADATA
langgraph_checkpoint_aerospike-0.1.0.dist-info/WHEEL
langgraph_checkpoint_aerospike-0.1.0.dist-info/top_level.txt
langgraph_checkpoint_aerospike-0.1.0.dist-info/RECORD
