Metadata-Version: 2.4
Name: langgraph-checkpoint-aerospike
Version: 0.1.0
Summary: Aerospike-based checkpoint saver for LangGraph
Author-email: "Aerospike, Inc." <info@aerospike.com>
License: Apache Software License
Project-URL: Repository, https://github.com/aerospike/aerospike-langgraph/tree/main/packages/langgraph-checkpoint-aerospike
Keywords: langgraph,aerospike,checkpoint
Classifier: License :: OSI Approved :: Apache Software License
Classifier: Programming Language :: Python :: 3
Classifier: Programming Language :: Python :: 3.10
Classifier: Programming Language :: Python :: 3.11
Classifier: Programming Language :: Python :: 3.12
Classifier: Topic :: Software Development :: Libraries :: Python Modules
Classifier: Topic :: Database
Requires-Python: >=3.10
Requires-Dist: langgraph>=0.6.0
Requires-Dist: aerospike>=15.0.0
